query2clips/__init__.py
query2clips/__main__.py
query2clips/filepaths.py
query2clips/install_ffmpeg.py
query2clips/pipeline/captioner/__init__.py
query2clips/pipeline/captioner/abc.py
query2clips/pipeline/captioner/gemini.py
query2clips/pipeline/clipper/__init__.py
query2clips/pipeline/clipper/abc.py
query2clips/pipeline/clipper/ffmpeg.py
query2clips/pipeline/downloader/__init__.py
query2clips/pipeline/downloader/abc.py
query2clips/pipeline/downloader/yt_dlp.py
query2clips/pipeline/searcher/__init__.py
query2clips/pipeline/searcher/abc.py
query2clips/pipeline/searcher/youtube.py
query2clips/query2clips.py
query2clips/video_utils/__init__.py
query2clips/video_utils/detect_cuts.py
query2clips/video_utils/extract_metadata.py
query2clips/video_utils/time_frame.py
query2clips-0.1.4.dist-info/METADATA
query2clips-0.1.4.dist-info/WHEEL
query2clips-0.1.4.dist-info/RECORD
